elasticgraph_mcp/__init__.py
elasticgraph_mcp/__main__.py
elasticgraph_mcp/errors.py
elasticgraph_mcp/helpers.py
elasticgraph_mcp/server.py
elasticgraph_mcp_server-0.1.1.dist-info/METADATA
elasticgraph_mcp_server-0.1.1.dist-info/WHEEL
elasticgraph_mcp_server-0.1.1.dist-info/entry_points.txt
elasticgraph_mcp_server-0.1.1.dist-info/RECORD
