Metadata-Version: 2.4
Name: elasticgraph-mcp-server
Version: 0.1.1
Summary: MCP Server for ElasticGraph to allow goose, Cursor, etc to create and manage your ElasticGraph project.
Project-URL: Homepage, https://block.github.io/elasticgraph/
Project-URL: Repository, https://github.com/block/elasticgraph
Author-email: Brian Sigafoos <briansigafoos@block.xyz>
License-Expression: MIT
Keywords: claude,cline,cursor,elasticgraph,mcp,model-context-protocol,windsurf
Classifier: Intended Audience :: Developers
Classifier: License :: OSI Approved :: MIT License
Classifier: Programming Language :: Python :: 3.12
Requires-Python: >=3.12
Requires-Dist: httpx>=0.28.1
Requires-Dist: mcp[cli]>=1.3.0
Requires-Dist: packaging>=23.0
